<mvc:View
    controllerName="app.l4desafio.app.controller.Gerenciar"
    xmlns:mvc="sap.ui.core.mvc"
    displayBlock="true"
    xmlns="sap.m"
>
	<Page showHeader="true" title="Gerenciar Equipes" titleAlignment="Center">
        <content>
            <Title text="Totais:" level="H3" class="sapUiTinyMarginBegin sapUiTinyMarginTop " />
                <ToolbarSpacer ></ToolbarSpacer>
                 <Button text="Funcionarios" press=".onShowTextInfo" width="100px" class="sapUiTinyMarginBegin sapUiSmallMarginBottom"/>
                    <Button text="Recursos Humanos" press=".onShowTextInfo" width="180px" class=" sapUiTinyMarginBegin sapUiSmallMarginBottom"/>
                        <Button text="Financeiro" press=".onShowTextInfo" width="100px" class="sapUiTinyMarginBegin sapUiSmallMarginBottom"/>
                            <Button text="Projetos" press=".onShowTextInfo" width="100px" class=" sapUiTinyMarginBegin sapUiSmallMarginBottom"/>
                                <ToolbarSpacer ></ToolbarSpacer>
              <Title text="Escolha a porcentagem:" level="H3" class="sapUiTinyMarginBegin sapUiTinyMarginTop " />
                <ToolbarSpacer ></ToolbarSpacer>

            	    	<Slider value="50" width="90%"
				            min="0" max="100"
				            showAdvancedTooltip="true"
				            showHandleTooltip="false"
				            class="sapUiMediumMarginBottom" />
                        <ToolbarSpacer ></ToolbarSpacer>
                        
                        <GenericTile class="sapUiTinyMarginBegin sapUiTinyMarginTop tileLayout" header="Funcionarios" subheader="Recursos Humanos" press="press">
		                    <TileContent unit="Unit" footer="Footer Text">
			                    <NumericContent value="10"  withMargin="false" />
		                    </TileContent>
	                    </GenericTile>
	                    <GenericTile class="sapUiTinyMarginBegin sapUiTinyMarginTop tileLayout" header="Funcionarios" subheader="Administração" press="press">
		                    <TileContent unit="Unit" footer="Footer Text">
			                    <NumericContent value="12" withMargin="false" />
		                    </TileContent>
	                    </GenericTile>
                        <GenericTile class="sapUiTinyMarginBegin sapUiTinyMarginTop tileLayout" header="Funcionarios" subheader="Desenvolvimento" press="press">
		                    <TileContent unit="Unit" footer="Footer Text">
			                    <NumericContent value="25" withMargin="false" />
		                    </TileContent>
	                    </GenericTile>

                          <ToolbarSpacer ></ToolbarSpacer>
                            <Button  text="Gerar Lista" press="onNavListar"  width="20%" class="sapUiTinyMarginBegin sapUiTinyMarginTop tileLayout" />          
        </content>
    </Page>		
</mvc:View>
